.gitignore
LICENSE
MANIFEST.in
README.md
requirements.txt
setup.cfg
setup.py
deviantart/__init__.py
deviantart/admin.py
deviantart/apps.py
deviantart/models.py
deviantart/oauth.py
deviantart/tests.py
deviantart/urls.py
deviantart/views.py
deviantart/migrations/0001_initial.py
deviantart/migrations/__init__.py
deviantart/templates/deviantart/endpoint.html
deviantart/templatetags/__init__.py
deviantart/templatetags/deviantart_tags.py
django_deviantart.egg-info/PKG-INFO
django_deviantart.egg-info/SOURCES.txt
django_deviantart.egg-info/dependency_links.txt
django_deviantart.egg-info/requires.txt
django_deviantart.egg-info/top_level.txt
djangodeviantartdemo/manage.py
djangodeviantartdemo/demo/__init__.py
djangodeviantartdemo/demo/admin.py
djangodeviantartdemo/demo/apps.py
djangodeviantartdemo/demo/models.py
djangodeviantartdemo/demo/tests.py
djangodeviantartdemo/demo/views.py
djangodeviantartdemo/demo/migrations/__init__.py
djangodeviantartdemo/demo/templates/profile.html
djangodeviantartdemo/djangodeviantartdemo/__init__.py
djangodeviantartdemo/djangodeviantartdemo/settings.py
djangodeviantartdemo/djangodeviantartdemo/urls.py
djangodeviantartdemo/djangodeviantartdemo/wsgi.py